PyGameBase/__init__.py
PyGameBase/animationtype.py
PyGameBase/cli.py
PyGameBase/desing.py
PyGameBase/image.py
pygamebase-0.1.2.dist-info/licenses/LICENSE
pygamebase-0.1.2.dist-info/METADATA
pygamebase-0.1.2.dist-info/WHEEL
pygamebase-0.1.2.dist-info/entry_points.txt
pygamebase-0.1.2.dist-info/top_level.txt
pygamebase-0.1.2.dist-info/RECORD
