Metadata-Version: 2.4
Name: PyGameBase
Version: 0.1.2
Summary: Biblioteca para facilitar o uso do Pygame com sintaxe mais simples e componentes prontos.
Home-page: https://github.com/programadoapp/pygamebase
Author: Thiago Silva Mendes
Author-email: devscriptpy@gmail.com
License: MIT
Keywords: pygame,jogos,2d,python,interface,PyGameBase
Classifier: Development Status :: 3 - Alpha
Classifier: Intended Audience :: Developers
Classifier: License :: OSI Approved :: MIT License
Classifier: Programming Language :: Python :: 3
Classifier: Programming Language :: Python :: 3.8
Classifier: Programming Language :: Python :: 3.9
Classifier: Programming Language :: Python :: 3.10
Classifier: Topic :: Games/Entertainment
Classifier: Operating System :: OS Independent
Requires-Python: >=3.8
License-File: LICENSE
Requires-Dist: pygame>=2.0.0
Requires-Dist: Pillow>=8.0.0
Dynamic: author
Dynamic: author-email
Dynamic: classifier
Dynamic: description
Dynamic: description-content-type
Dynamic: home-page
Dynamic: keywords
Dynamic: license
Dynamic: license-file
Dynamic: requires-dist
Dynamic: requires-python
Dynamic: summary
